bingx/__init__.py
bingx/api.py
bingx/exceptions.py
bingx/utilities.py
py_bingx-0.4.dist-info/LICENSE
py_bingx-0.4.dist-info/METADATA
py_bingx-0.4.dist-info/WHEEL
py_bingx-0.4.dist-info/top_level.txt
py_bingx-0.4.dist-info/RECORD
